libname/__init__.py
libname/topsis.py
topsis_karanveer_102303670-0.0.9.dist-info/METADATA
topsis_karanveer_102303670-0.0.9.dist-info/WHEEL
topsis_karanveer_102303670-0.0.9.dist-info/top_level.txt
topsis_karanveer_102303670-0.0.9.dist-info/RECORD
