Metadata-Version: 2.4
Name: Topsis-Karanveer-102303670
Version: 0.0.9
Summary: topsis
Author: Karanveer Singh
Author-email: karanveer135790@gmail.com
Keywords: python,topsis,ranking,decision making,mcdm
Classifier: Development Status :: 3 - Alpha
Classifier: Intended Audience :: Developers
Classifier: Programming Language :: Python :: 3
Classifier: Operating System :: Unix
Classifier: Operating System :: MacOS :: MacOS X
Classifier: Operating System :: Microsoft :: Windows
Requires-Dist: pandas
Requires-Dist: numpy
Dynamic: author
Dynamic: author-email
Dynamic: classifier
Dynamic: description
Dynamic: description-content-type
Dynamic: keywords
Dynamic: requires-dist
Dynamic: summary
